Gowtham_STT/__init__.py
Gowtham_STT/main.py
Gowtham_STT-1.2.0.dist-info/METADATA
Gowtham_STT-1.2.0.dist-info/WHEEL
Gowtham_STT-1.2.0.dist-info/top_level.txt
Gowtham_STT-1.2.0.dist-info/RECORD
