Metadata-Version: 2.1
Name: Gowtham_STT
Version: 1.2.0
Summary: A Speech To Text By Gowtham with HTML, CSS, JS, and Python files
Author: Gowtham
Classifier: Programming Language :: Python :: 3
Classifier: License :: OSI Approved :: MIT License
Classifier: Operating System :: OS Independent
Requires-Python: >=3.6
Requires-Dist: selenium
Requires-Dist: webdriver-manager
